fadids/__init__.py
fadids/api.py
fadids/models/__init__.py
fadids/models/container.py
fadids/models/multivariate.py
fadids/models/univariate.py
fadids/utils/__init__.py
fadids/utils/simulator.py
test/__init__.py
test/test_mean_deviation.py
test/test_simulator.py
fadids-0.32.dist-info/METADATA
fadids-0.32.dist-info/WHEEL
fadids-0.32.dist-info/top_level.txt
fadids-0.32.dist-info/RECORD
