Metadata-Version: 2.1
Name: fadids
Version: 0.32
Summary: Personal
Home-page: UNKNOWN
Author: Rémi Prince
License: UNKNOWN
Platform: UNKNOWN
Requires-Python: >=3.8
Requires-Dist: numpy
Requires-Dist: scikit-learn
Requires-Dist: streamad
